[
  {
    "id": "G&S",
    "name": "GRIMM & SONS",
    "light": "#003B47",
    "dark": "#0DC2EE",
    "logo_url": "https://svgshare.com/i/zjj.svg",
    "quote": "Working For the Promised Land",
    "description": "Grimm & Sons are a corpro-state built out of the great ProleClans of Lonely Cradle, the full power of a republic of toil set to taming the stars in the name of humanity at large. Their mechs are like they are- sturdy, tough, and meant to build the better world their pilots dream of."
  }
]